raydium_sdk/__init__.py
raydium_sdk/utils/create_close_account.py
raydium_sdk/utils/dexscreener.py
raydium_sdk-2.1.3.dist-info/METADATA
raydium_sdk-2.1.3.dist-info/WHEEL
raydium_sdk-2.1.3.dist-info/RECORD
